hydromt_geb/__init__.py
hydromt_geb/geb.py
hydromt_geb/custom_models/__init__.py
hydromt_geb/custom_models/fairstream.py
hydromt_geb/workflows/__init__.py
hydromt_geb/workflows/crop_calendars.py
hydromt_geb/workflows/farmers.py
hydromt_geb/workflows/general.py
hydromt_geb/workflows/population.py
hydromt_geb/workflows/soilgrids.py
hydromt_geb-1.0.0.dev2.dist-info/entry_points.txt
hydromt_geb-1.0.0.dev2.dist-info/WHEEL
hydromt_geb-1.0.0.dev2.dist-info/METADATA
hydromt_geb-1.0.0.dev2.dist-info/RECORD
