Metadata-Version: 2.1
Name: hydromt_geb
Version: 1.0.0.dev2
Summary: hydroMT plugin for GEB models.
Author-email: Jens de Bruijn <jens.de.bruijn@vu.nl>, Maurice Kalthof <w.m.l.kalthof@vu.nl>, Tim Busker <tim.busker@vu.nl>
Requires-Python: >=3.11
Classifier: Development Status :: 4 - Beta
Classifier: Intended Audience :: Developers
Classifier: Intended Audience :: Science/Research
Classifier: Topic :: Scientific/Engineering :: Hydrology
Classifier: License :: OSI Approved :: GNU General Public License v3 (GPLv3)
Classifier: Programming Language :: Python :: 3
Requires-Dist: s3fs>=2023.6.0
Requires-Dist: xesmf>=0.8.4
Requires-Dist: hydromt==0.10.0
Requires-Dist: tqdm>=4.66.1
Requires-Dist: openpyxl>=3.1.2
Requires-Dist: isimip-client>=1.0.1
Requires-Dist: xclim>=0.44.0
Requires-Dist: pyogrio>=0.7
Requires-Dist: pyrosm>=0.6.2
Requires-Dist: cdsapi>=0.7.0
Requires-Dist: rioxarray
Requires-Dist: geopandas>=1.0.0
Requires-Dist: honeybees
Requires-Dist: pgmpy>=0.1.24 ; extra == "fairstream"
Requires-Dist: daft>=0.1.2 ; extra == "fairstream"
Requires-Dist: opt-einsum>=3.3.0 ; extra == "fairstream"
Requires-Dist: pytest ; extra == "tests"
Provides-Extra: doc
Provides-Extra: fairstream
Provides-Extra: full
Provides-Extra: tests
